bin/vini
vini/AveragePlot.py
vini/ColorMapItem.py
vini/ColorMapWidget.py
vini/FunctionalDialog.py
vini/HistogramThresholdWidget.py
vini/Image.py
vini/Image3D.py
vini/Image4D.py
vini/ImageDialog.py
vini/ImageItemMod.py
vini/JumpSlider.py
vini/MosaicDialog.py
vini/MosaicSliceBox.py
vini/MosaicView.py
vini/QxtSpanSlider.py
vini/QxtSpanSliderH.py
vini/SettingsDialog.py
vini/SingleSlice.py
vini/SliceBox.py
vini/SliceWidget.py
vini/SliceWindow.py
vini/TimePlot.py
vini/ValueWindow.py
vini/Verboseprint.py
vini/VistaLoad.py
vini/__init__.py
vini/_cli_wrapper.py
vini/loadImage.py
vini/python2_3.py
vini/qt.py
vini/qt_console_widget.py
vini/qt_loaders.py
vini/quaternions.py
vini/resample.py
vini/testInputs.py
vini/transformations.py
vini/viewer.py
vini/icons/__init__.py
vini/icons/app_icon.svg
vini/icons/check.svg
vini/icons/chevron-down.svg
vini/icons/chevron-up.svg
vini/icons/cross.svg
vini/icons/cursor.svg
vini/icons/dash.svg
vini/icons/fastback.svg
vini/icons/fastfor.svg
vini/icons/link.svg
vini/icons/mail-reply.svg
vini/icons/max.svg
vini/icons/min.svg
vini/icons/next.svg
vini/icons/pause.svg
vini/icons/plus.svg
vini/icons/prev.svg
vini/icons/reset.svg
vini/icons/tleft.svg
vini/icons/triangle-left.svg
vini/icons/triangle-right.svg
vini/icons/voxel.svg
vini/pyqtgraph_vini/PlotData.py
vini/pyqtgraph_vini/Point.py
vini/pyqtgraph_vini/Qt.py
vini/pyqtgraph_vini/Qtlk.py
vini/pyqtgraph_vini/SRTTransform.py
vini/pyqtgraph_vini/SRTTransform3D.py
vini/pyqtgraph_vini/SignalProxy.py
vini/pyqtgraph_vini/ThreadsafeTimer.py
vini/pyqtgraph_vini/Transform3D.py
vini/pyqtgraph_vini/Vector.py
vini/pyqtgraph_vini/WidgetGroup.py
vini/pyqtgraph_vini/__init__.py
vini/pyqtgraph_vini/colormap.py
vini/pyqtgraph_vini/configfile.py
vini/pyqtgraph_vini/debug.py
vini/pyqtgraph_vini/exceptionHandling.py
vini/pyqtgraph_vini/frozenSupport.py
vini/pyqtgraph_vini/functions.py
vini/pyqtgraph_vini/graphicsWindows.py
vini/pyqtgraph_vini/numpy_fix.py
vini/pyqtgraph_vini/ordereddict.py
vini-1.0.0.dist-info/licenses/LICENSE
vini-1.0.0.dist-info/METADATA
vini-1.0.0.dist-info/WHEEL
vini-1.0.0.dist-info/entry_points.txt
vini-1.0.0.dist-info/top_level.txt
vini-1.0.0.dist-info/RECORD
