Metadata-Version: 2.4
Name: vini
Version: 1.0.0
Summary: A visualization tool for 2D/3D/4D data (e.g. from MRI)
Home-page: 
Author: Malte Kuhlmann, Eric Lacosse, Johannes Stelzer, Lucas Mahler, Amelie Flietel
Author-email: 
License-Expression: MIT
Project-URL: Homepage, https://github.com/MPI-Neuroinformatics/vini
Classifier: Programming Language :: Python
Classifier: Programming Language :: Python :: 3
Classifier: Programming Language :: Python :: 3.6
Classifier: Programming Language :: Python :: Implementation :: CPython
Classifier: Programming Language :: Python :: Implementation :: PyPy
Requires-Python: >=3.5.0
License-File: LICENSE
Requires-Dist: ipython
Requires-Dist: nibabel
Requires-Dist: numpy
Requires-Dist: scipy
Requires-Dist: matplotlib
Requires-Dist: sip
Dynamic: license-file
Dynamic: requires-python
